README.txt
setup.py
facechat/__init__.py
facechat/ai/__init__.py
facechat/ai/autoencoder/__init__.py
facechat/ai/autoencoder/agn.py
facechat/ai/autoencoder/test.py
facechat/ai/cnn/__init__.py
facechat/ai/cnn/cifar10.py
facechat/ai/cnn/mnist.py
facechat/ai/data/__init__.py
facechat/ai/data/reader.py
facechat/ai/data/writer.py
facechat/ai/rl/__init__.py
facechat/ai/rnn/__init__.py
facechat/ai/simple/__init__.py
facechat/ai/simple/softmax.py
facechat/ai/tool/__init__.py
facechat/ai/tool/properties.py
facechat/ai/web/__init__.py
facechat/ai/web/api.py
facechat_ai.egg-info/PKG-INFO
facechat_ai.egg-info/SOURCES.txt
facechat_ai.egg-info/dependency_links.txt
facechat_ai.egg-info/top_level.txt