Metadata-Version: 1.0
Name: facechat-ai
Version: 1.0.0.4
Summary: this is the facechat-ai which can help you build the deeplearning quickly
Home-page: http://tikiapp.im
Author: geekbruce
Author-email: bruce.shaoheng@gmail.com
License: UNKNOWN
Platform: UNKNOWN
